[
  {
    "id": "kamilkisiela_graphql-inspector_packages_action",
    "name": "graphql-inspector",
    "owner": "kamilkisiela",
    "path": "packages/action",
    "pkg": "@graphql-inspector/action"
  },
  {
    "id": "kamilkisiela_apollo-angular",
    "name": "apollo-angular",
    "owner": "kamilkisiela"
  },
  {
    "id": "n1ru4l_envelop_packages_plugins_apollo-datasources",
    "name": "envelop",
    "owner": "n1ru4l",
    "path": "packages/plugins/apollo-datasources",
    "pkg": "@envelop/apollo-datasources"
  },
  {
    "id": "n1ru4l_envelop_packages_plugins_apollo-federation",
    "name": "envelop",
    "owner": "n1ru4l",
    "path": "packages/plugins/apollo-federation",
    "pkg": "@envelop/apollo-federation"
  },
  {
    "id": "n1ru4l_envelop_packages_plugins_apollo-server-errors",
    "name": "envelop",
    "owner": "n1ru4l",
    "path": "packages/plugins/apollo-server-errors",
    "pkg": "@envelop/apollo-server-errors"
  },
  {
    "id": "n1ru4l_envelop_packages_plugins_apollo-tracing",
    "name": "envelop",
    "owner": "n1ru4l",
    "path": "packages/plugins/apollo-tracing",
    "pkg": "@envelop/apollo-tracing"
  },
  {
    "id": "kamilkisiela_graphql-inspector_packages_commands_audit",
    "name": "graphql-inspector",
    "owner": "kamilkisiela",
    "path": "packages/commands/audit",
    "pkg": "@graphql-inspector/audit-command"
  },
  {
    "id": "n1ru4l_envelop_packages_plugins_auth0",
    "name": "envelop",
    "owner": "n1ru4l",
    "path": "packages/plugins/auth0",
    "pkg": "@envelop/auth0"
  },
  {
    "id": "kamilkisiela_graphql-inspector_packages_ci",
    "name": "graphql-inspector",
    "owner": "kamilkisiela",
    "path": "packages/ci",
    "pkg": "@graphql-inspector/ci"
  },
  {
    "id": "kamilkisiela_graphql-inspector_packages_cli",
    "name": "graphql-inspector",
    "owner": "kamilkisiela",
    "path": "packages/cli",
    "pkg": "@graphql-inspector/cli"
  },
  {
    "id": "kamilkisiela_graphql-inspector_packages_loaders_code",
    "name": "graphql-inspector",
    "owner": "kamilkisiela",
    "path": "packages/loaders/code",
    "pkg": "@graphql-inspector/code-loader"
  },
  {
    "id": "kamilkisiela_graphql-inspector_packages_commands_commands",
    "name": "graphql-inspector",
    "owner": "kamilkisiela",
    "path": "packages/commands/commands",
    "pkg": "@graphql-inspector/commands"
  },
  {
    "id": "kamilkisiela_graphql-inspector_packages_config",
    "name": "graphql-inspector",
    "owner": "kamilkisiela",
    "path": "packages/config",
    "pkg": "@graphql-inspector/config"
  },
  {
    "id": "kamilkisiela_graphql-inspector_packages_core",
    "name": "graphql-inspector",
    "owner": "kamilkisiela",
    "path": "packages/core",
    "pkg": "@graphql-inspector/core"
  },
  {
    "id": "n1ru4l_envelop_packages_core",
    "name": "envelop",
    "owner": "n1ru4l",
    "path": "packages/core",
    "pkg": "@envelop/core"
  },
  {
    "id": "kamilkisiela_graphql-inspector_packages_commands_coverage",
    "name": "graphql-inspector",
    "owner": "kamilkisiela",
    "path": "packages/commands/coverage",
    "pkg": "@graphql-inspector/coverage-command"
  },
  {
    "id": "n1ru4l_envelop_packages_plugins_dataloader",
    "name": "envelop",
    "owner": "n1ru4l",
    "path": "packages/plugins/dataloader",
    "pkg": "@envelop/dataloader"
  },
  {
    "id": "n1ru4l_envelop_packages_plugins_depth-limit",
    "name": "envelop",
    "owner": "n1ru4l",
    "path": "packages/plugins/depth-limit",
    "pkg": "@envelop/depth-limit"
  },
  {
    "id": "kamilkisiela_graphql-inspector_packages_commands_diff",
    "name": "graphql-inspector",
    "owner": "kamilkisiela",
    "path": "packages/commands/diff",
    "pkg": "@graphql-inspector/diff-command"
  },
  {
    "id": "n1ru4l_envelop_packages_plugins_disable-introspection",
    "name": "envelop",
    "owner": "n1ru4l",
    "path": "packages/plugins/disable-introspection",
    "pkg": "@envelop/disable-introspection"
  },
  {
    "id": "kamilkisiela_graphql-inspector_packages_commands_docs",
    "name": "graphql-inspector",
    "owner": "kamilkisiela",
    "path": "packages/commands/docs",
    "pkg": "@graphql-inspector/docs-command"
  },
  {
    "id": "n1ru4l_envelop",
    "name": "envelop",
    "owner": "n1ru4l"
  },
  {
    "id": "n1ru4l_envelop_packages_plugins",
    "name": "envelop",
    "owner": "n1ru4l",
    "path": "packages/plugins"
  },
  {
    "id": "n1ru4l_envelop_packages_plugins_execute-subscription-event",
    "name": "envelop",
    "owner": "n1ru4l",
    "path": "packages/plugins/execute-subscription-event",
    "pkg": "@envelop/execute-subscription-event"
  },
  {
    "id": "n1ru4l_envelop_packages_plugins_extended-validation",
    "name": "envelop",
    "owner": "n1ru4l",
    "path": "packages/plugins/extended-validation",
    "pkg": "@envelop/extended-validation"
  },
  {
    "id": "n1ru4l_envelop_packages_plugins_filter-operation-type",
    "name": "envelop",
    "owner": "n1ru4l",
    "path": "packages/plugins/filter-operation-type",
    "pkg": "@envelop/filter-operation-type"
  },
  {
    "id": "n1ru4l_envelop_packages_plugins_fragment-arguments",
    "name": "envelop",
    "owner": "n1ru4l",
    "path": "packages/plugins/fragment-arguments",
    "pkg": "@envelop/fragment-arguments"
  },
  {
    "id": "n1ru4l_envelop_packages_plugins_generic-auth",
    "name": "envelop",
    "owner": "n1ru4l",
    "path": "packages/plugins/generic-auth",
    "pkg": "@envelop/generic-auth"
  },
  {
    "id": "kamilkisiela_graphql-inspector_packages_loaders_git",
    "name": "graphql-inspector",
    "owner": "kamilkisiela",
    "path": "packages/loaders/git",
    "pkg": "@graphql-inspector/git-loader"
  },
  {
    "id": "kamilkisiela_graphql-inspector_packages_github",
    "name": "graphql-inspector",
    "owner": "kamilkisiela",
    "path": "packages/github",
    "pkg": "@graphql-inspector/github"
  },
  {
    "id": "kamilkisiela_graphql-inspector_packages_loaders_github",
    "name": "graphql-inspector",
    "owner": "kamilkisiela",
    "path": "packages/loaders/github",
    "pkg": "@graphql-inspector/github-loader"
  },
  {
    "id": "kamilkisiela_graphql-config",
    "name": "graphql-config",
    "owner": "kamilkisiela",
    "pkg": "graphql-config"
  },
  {
    "id": "kamilkisiela_graphql-hive",
    "name": "graphql-hive",
    "owner": "kamilkisiela"
  },
  {
    "id": "kamilkisiela_graphql-inspector",
    "name": "graphql-inspector",
    "owner": "kamilkisiela"
  },
  {
    "id": "kamilkisiela_graphql-inspector_packages_commands",
    "name": "graphql-inspector",
    "owner": "kamilkisiela",
    "path": "packages/commands"
  },
  {
    "id": "kamilkisiela_graphql-inspector_packages_graphql-cli",
    "name": "graphql-inspector",
    "owner": "kamilkisiela",
    "path": "packages/graphql-cli"
  },
  {
    "id": "kamilkisiela_graphql-inspector_packages_loaders",
    "name": "graphql-inspector",
    "owner": "kamilkisiela",
    "path": "packages/loaders"
  },
  {
    "id": "kamilkisiela_graphql-inspector_packages_testing",
    "name": "graphql-inspector",
    "owner": "kamilkisiela",
    "path": "packages/testing"
  },
  {
    "id": "n1ru4l_envelop_packages_plugins_graphql-jit",
    "name": "envelop",
    "owner": "n1ru4l",
    "path": "packages/plugins/graphql-jit",
    "pkg": "@envelop/graphql-jit"
  },
  {
    "id": "n1ru4l_graphql-live-query",
    "name": "graphql-live-query",
    "owner": "n1ru4l"
  },
  {
    "id": "n1ru4l_graphql-live-query_packages_graphql-live-query",
    "name": "graphql-live-query",
    "owner": "n1ru4l",
    "path": "packages/graphql-live-query",
    "pkg": "@n1ru4l/graphql-live-query"
  },
  {
    "id": "n1ru4l_graphql-live-query_packages_todo-example",
    "name": "graphql-live-query",
    "owner": "n1ru4l",
    "path": "packages/todo-example"
  },
  {
    "id": "n1ru4l_graphql-live-query_packages_graphql-live-query-patch",
    "name": "graphql-live-query",
    "owner": "n1ru4l",
    "path": "packages/graphql-live-query-patch",
    "pkg": "@n1ru4l/graphql-live-query-patch"
  },
  {
    "id": "n1ru4l_graphql-live-query_packages_graphql-live-query-patch-json-patch",
    "name": "graphql-live-query",
    "owner": "n1ru4l",
    "path": "packages/graphql-live-query-patch-json-patch",
    "pkg": "@n1ru4l/graphql-live-query-patch-json-patch"
  },
  {
    "id": "n1ru4l_graphql-live-query_packages_graphql-live-query-patch-jsondiffpatch",
    "name": "graphql-live-query",
    "owner": "n1ru4l",
    "path": "packages/graphql-live-query-patch-jsondiffpatch",
    "pkg": "@n1ru4l/graphql-live-query-patch-jsondiffpatch"
  },
  {
    "id": "kamilkisiela_graphql-inspector_packages_loaders_graphql",
    "name": "graphql-inspector",
    "owner": "kamilkisiela",
    "path": "packages/loaders/graphql",
    "pkg": "@graphql-inspector/graphql-loader"
  },
  {
    "id": "n1ru4l_envelop_packages_plugins_graphql-middleware",
    "name": "envelop",
    "owner": "n1ru4l",
    "path": "packages/plugins/graphql-middleware",
    "pkg": "@envelop/graphql-middleware"
  },
  {
    "id": "n1ru4l_envelop_packages_plugins_graphql-modules",
    "name": "envelop",
    "owner": "n1ru4l",
    "path": "packages/plugins/graphql-modules",
    "pkg": "@envelop/graphql-modules"
  },
  {
    "id": "n1ru4l_graphql-public-schema-filter",
    "name": "graphql-public-schema-filter",
    "owner": "n1ru4l",
    "pkg": "@n1ru4l/graphql-public-schema-filter"
  },
  {
    "id": "n1ru4l_envelop_packages_plugins_immediate-introspection",
    "name": "envelop",
    "owner": "n1ru4l",
    "path": "packages/plugins/immediate-introspection",
    "pkg": "@envelop/immediate-introspection"
  },
  {
    "id": "n1ru4l_graphql-live-query_packages_in-memory-live-query-store",
    "name": "graphql-live-query",
    "owner": "n1ru4l",
    "path": "packages/in-memory-live-query-store",
    "pkg": "@n1ru4l/in-memory-live-query-store"
  },
  {
    "id": "kamilkisiela_graphql-inspector_packages_commands_introspect",
    "name": "graphql-inspector",
    "owner": "kamilkisiela",
    "path": "packages/commands/introspect",
    "pkg": "@graphql-inspector/introspect-command"
  },
  {
    "id": "kamilkisiela_graphql-inspector_packages_loaders_json",
    "name": "graphql-inspector",
    "owner": "kamilkisiela",
    "path": "packages/loaders/json",
    "pkg": "@graphql-inspector/json-loader"
  },
  {
    "id": "n1ru4l_graphql-live-query_packages_json-patch-plus",
    "name": "graphql-live-query",
    "owner": "n1ru4l",
    "path": "packages/json-patch-plus",
    "pkg": "@n1ru4l/json-patch-plus"
  },
  {
    "id": "n1ru4l_envelop_packages_plugins_live-query",
    "name": "envelop",
    "owner": "n1ru4l",
    "path": "packages/plugins/live-query",
    "pkg": "@envelop/live-query"
  },
  {
    "id": "kamilkisiela_graphql-inspector_packages_loaders_loaders",
    "name": "graphql-inspector",
    "owner": "kamilkisiela",
    "path": "packages/loaders/loaders",
    "pkg": "@graphql-inspector/loaders"
  },
  {
    "id": "kamilkisiela_graphql-inspector_packages_logger",
    "name": "graphql-inspector",
    "owner": "kamilkisiela",
    "path": "packages/logger",
    "pkg": "@graphql-inspector/logger"
  },
  {
    "id": "n1ru4l_envelop_packages_plugins_newrelic",
    "name": "envelop",
    "owner": "n1ru4l",
    "path": "packages/plugins/newrelic",
    "pkg": "@envelop/newrelic"
  },
  {
    "id": "n1ru4l_envelop_packages_plugins_on-resolve",
    "name": "envelop",
    "owner": "n1ru4l",
    "path": "packages/plugins/on-resolve",
    "pkg": "@envelop/on-resolve"
  },
  {
    "id": "n1ru4l_envelop_packages_plugins_opentelemetry",
    "name": "envelop",
    "owner": "n1ru4l",
    "path": "packages/plugins/opentelemetry",
    "pkg": "@envelop/opentelemetry"
  },
  {
    "id": "n1ru4l_envelop_packages_plugins_operation-field-permissions",
    "name": "envelop",
    "owner": "n1ru4l",
    "path": "packages/plugins/operation-field-permissions",
    "pkg": "@envelop/operation-field-permissions"
  },
  {
    "id": "n1ru4l_envelop_packages_plugins_parser-cache",
    "name": "envelop",
    "owner": "n1ru4l",
    "path": "packages/plugins/parser-cache",
    "pkg": "@envelop/parser-cache"
  },
  {
    "id": "n1ru4l_envelop_packages_plugins_persisted-operations",
    "name": "envelop",
    "owner": "n1ru4l",
    "path": "packages/plugins/persisted-operations",
    "pkg": "@envelop/persisted-operations"
  },
  {
    "id": "n1ru4l_envelop_packages_plugins_preload-assets",
    "name": "envelop",
    "owner": "n1ru4l",
    "path": "packages/plugins/preload-assets",
    "pkg": "@envelop/preload-assets"
  },
  {
    "id": "n1ru4l_envelop_packages_plugins_prometheus",
    "name": "envelop",
    "owner": "n1ru4l",
    "path": "packages/plugins/prometheus",
    "pkg": "@envelop/prometheus"
  },
  {
    "id": "n1ru4l_envelop_packages_plugins_rate-limiter",
    "name": "envelop",
    "owner": "n1ru4l",
    "path": "packages/plugins/rate-limiter",
    "pkg": "@envelop/rate-limiter"
  },
  {
    "id": "n1ru4l_envelop_packages_plugins_resource-limitations",
    "name": "envelop",
    "owner": "n1ru4l",
    "path": "packages/plugins/resource-limitations",
    "pkg": "@envelop/resource-limitations"
  },
  {
    "id": "n1ru4l_envelop_packages_plugins_response-cache",
    "name": "envelop",
    "owner": "n1ru4l",
    "path": "packages/plugins/response-cache",
    "pkg": "@envelop/response-cache"
  },
  {
    "id": "n1ru4l_envelop_packages_plugins_response-cache-redis",
    "name": "envelop",
    "owner": "n1ru4l",
    "path": "packages/plugins/response-cache-redis",
    "pkg": "@envelop/response-cache-redis"
  },
  {
    "id": "n1ru4l_envelop_packages_plugins_sentry",
    "name": "envelop",
    "owner": "n1ru4l",
    "path": "packages/plugins/sentry",
    "pkg": "@envelop/sentry"
  },
  {
    "id": "kamilkisiela_graphql-inspector_packages_commands_serve",
    "name": "graphql-inspector",
    "owner": "kamilkisiela",
    "path": "packages/commands/serve",
    "pkg": "@graphql-inspector/serve-command"
  },
  {
    "id": "kamilkisiela_graphql-inspector_packages_commands_similar",
    "name": "graphql-inspector",
    "owner": "kamilkisiela",
    "path": "packages/commands/similar",
    "pkg": "@graphql-inspector/similar-command"
  },
  {
    "id": "n1ru4l_graphql-live-query_packages_socket-io-graphql-client",
    "name": "graphql-live-query",
    "owner": "n1ru4l",
    "path": "packages/socket-io-graphql-client",
    "pkg": "@n1ru4l/socket-io-graphql-client"
  },
  {
    "id": "n1ru4l_graphql-live-query_packages_socket-io-graphql-server",
    "name": "graphql-live-query",
    "owner": "n1ru4l",
    "path": "packages/socket-io-graphql-server",
    "pkg": "@n1ru4l/socket-io-graphql-server"
  },
  {
    "id": "n1ru4l_envelop_packages_plugins_statsd",
    "name": "envelop",
    "owner": "n1ru4l",
    "path": "packages/plugins/statsd",
    "pkg": "@envelop/statsd"
  },
  {
    "id": "n1ru4l_envelop_packages_testing",
    "name": "envelop",
    "owner": "n1ru4l",
    "path": "packages/testing",
    "pkg": "@envelop/testing"
  },
  {
    "id": "n1ru4l_envelop_packages_types",
    "name": "envelop",
    "owner": "n1ru4l",
    "path": "packages/types",
    "pkg": "@envelop/types"
  },
  {
    "id": "kamilkisiela_graphql-inspector_packages_loaders_url",
    "name": "graphql-inspector",
    "owner": "kamilkisiela",
    "path": "packages/loaders/url",
    "pkg": "@graphql-inspector/url-loader"
  },
  {
    "id": "kamilkisiela_graphql-inspector_packages_commands_validate",
    "name": "graphql-inspector",
    "owner": "kamilkisiela",
    "path": "packages/commands/validate",
    "pkg": "@graphql-inspector/validate-command"
  },
  {
    "id": "n1ru4l_envelop_packages_plugins_validation-cache",
    "name": "envelop",
    "owner": "n1ru4l",
    "path": "packages/plugins/validation-cache",
    "pkg": "@envelop/validation-cache"
  }
]